pkg_support_resistance-0.4.3.dist-info/METADATA
pkg_support_resistance-0.4.3.dist-info/WHEEL
pkg_support_resistance-0.4.3.dist-info/licenses/LICENSE
pkg_support_resistance/__init__.py
pkg_support_resistance/data_set/__init__.py
pkg_support_resistance/data_set/example.py
pkg_support_resistance/dbscan/__init__.py
pkg_support_resistance/dbscan/dbscan_algo.c
pkg_support_resistance/dbscan/dbscan_algo.py
pkg_support_resistance/dbscan/dbscan_algo_dev.ipynb
pkg_support_resistance/dbscan/plot/__init__.py
pkg_support_resistance/dbscan/plot/dbscan_algo_plot.png
pkg_support_resistance/kmeans/__init__.py
pkg_support_resistance/kmeans/kmeans_algo.c
pkg_support_resistance/kmeans/kmeans_algo.py
pkg_support_resistance/kmeans/kmeans_algo_dev.ipynb
pkg_support_resistance/kmeans/plot/__init__.py
pkg_support_resistance/kmeans/plot/kmeans_algo_plot.png
pkg_support_resistance/setup.py
pkg_support_resistance/vanilla/__init__.py
pkg_support_resistance/vanilla/plot/__init__.py
pkg_support_resistance/vanilla/plot/vanilla_algo_plot.png
pkg_support_resistance/vanilla/vanilla_algo.c
pkg_support_resistance/vanilla/vanilla_algo.py
pkg_support_resistance/vanilla/vanilla_algo_dev.ipynb
pkg_support_resistance-0.4.3.dist-info/RECORD
