Metadata-Version: 2.1
Name: pkg-support-resistance
Version: 0.4.3
Summary: Library collection of algorithms to calculate supports and resistance of financial markets.
Author-Email: pablo brocal <pablomb206@gmail.com>
License: MIT
Project-URL: Repository, https://github.com/pablob206/pkg-support-resistance
Project-URL: Homepage, https://github.com/pablob206/pkg-support-resistance
Requires-Python: >=3.12
Requires-Dist: numpy>=1.26.4
Requires-Dist: scikit-learn>=1.5.0
Requires-Dist: pandas>=2.2.2
